tempo_random/__init__.py
tempo_random/functions.py
tempo_random/main.py
tempo_random-0.1.0.dist-info/entry_points.txt
tempo_random-0.1.0.dist-info/WHEEL
tempo_random-0.1.0.dist-info/METADATA
tempo_random-0.1.0.dist-info/RECORD
